macrocosmos/__init__.py
macrocosmos/billing_client.py
macrocosmos/gravity_client.py
macrocosmos/logger_client.py
macrocosmos/sn13_client.py
macrocosmos/generated/__init__.py
macrocosmos/generated/billing/__init__.py
macrocosmos/generated/billing/v1/__init__.py
macrocosmos/generated/billing/v1/billing_p2p.py
macrocosmos/generated/billing/v1/billing_pb2.py
macrocosmos/generated/billing/v1/billing_pb2.pyi
macrocosmos/generated/billing/v1/billing_pb2_grpc.py
macrocosmos/generated/gravity/__init__.py
macrocosmos/generated/gravity/v1/__init__.py
macrocosmos/generated/gravity/v1/gravity_p2p.py
macrocosmos/generated/gravity/v1/gravity_pb2.py
macrocosmos/generated/gravity/v1/gravity_pb2.pyi
macrocosmos/generated/gravity/v1/gravity_pb2_grpc.py
macrocosmos/generated/logger/__init__.py
macrocosmos/generated/logger/v1/__init__.py
macrocosmos/generated/logger/v1/logger_p2p.py
macrocosmos/generated/logger/v1/logger_pb2.py
macrocosmos/generated/logger/v1/logger_pb2.pyi
macrocosmos/generated/logger/v1/logger_pb2_grpc.py
macrocosmos/generated/models/__init__.py
macrocosmos/generated/sn13/__init__.py
macrocosmos/generated/sn13/v1/__init__.py
macrocosmos/generated/sn13/v1/sn13_validator_p2p.py
macrocosmos/generated/sn13/v1/sn13_validator_pb2.py
macrocosmos/generated/sn13/v1/sn13_validator_pb2.pyi
macrocosmos/generated/sn13/v1/sn13_validator_pb2_grpc.py
macrocosmos/resources/__init__.py
macrocosmos/resources/_client.py
macrocosmos/resources/_stream.py
macrocosmos/resources/_utils.py
macrocosmos/resources/billing.py
macrocosmos/resources/gravity.py
macrocosmos/resources/logger.py
macrocosmos/resources/sn13.py
macrocosmos/resources/logging/README.md
macrocosmos/resources/logging/__init__.py
macrocosmos/resources/logging/console_handler.py
macrocosmos/resources/logging/file_manager.py
macrocosmos/resources/logging/file_monitor.py
macrocosmos/resources/logging/request.py
macrocosmos/resources/logging/run.py
macrocosmos/resources/logging/upload_worker.py
macrocosmos/types/__init__.py
macrocosmos-3.1.0.dist-info/METADATA
macrocosmos-3.1.0.dist-info/WHEEL
macrocosmos-3.1.0.dist-info/licenses/LICENSE
macrocosmos-3.1.0.dist-info/licenses/NOTICE
macrocosmos-3.1.0.dist-info/RECORD
