Metadata-Version: 2.4
Name: macrocosmos
Version: 3.1.0
Summary: The official Python SDK for Macrocosmos
Author-email: Macrocosmos <support@macrocosmos.ai>
License-Expression: Apache-2.0
License-File: LICENSE
License-File: NOTICE
Requires-Python: >=3.8
Requires-Dist: grpcio-tools>=1.70.0
Requires-Dist: grpcio>=1.70.0
Requires-Dist: protobuf<6.0.0,>=5.29.5
Requires-Dist: pydantic>=2.10.6
